elifedbtools/__init__.py
elifedbtools-0.0.1.dist-info/DESCRIPTION.rst
elifedbtools-0.0.1.dist-info/METADATA
elifedbtools-0.0.1.dist-info/metadata.json
elifedbtools-0.0.1.dist-info/RECORD
elifedbtools-0.0.1.dist-info/top_level.txt
elifedbtools-0.0.1.dist-info/WHEEL
